jw8507.cp311-win_amd64.pyd
jw8507-0.1.2.dist-info/LICENSE
jw8507-0.1.2.dist-info/METADATA
jw8507-0.1.2.dist-info/WHEEL
jw8507-0.1.2.dist-info/top_level.txt
jw8507-0.1.2.dist-info/RECORD
