Metadata-Version: 2.1
Name: jw8507
Version: 0.1.2
Summary: JW8507 is a device of optical attenator
Home-page: https://github.com/JerryZheng89/jw8507_whl
Author: Jerry Zheng
Author-email: JerryZheng2018@outlook.com
License: CC BY-NC 4.0
Classifier: Operating System :: MacOS :: MacOS X
Classifier: Operating System :: POSIX :: Linux
Classifier: Operating System :: Microsoft :: Windows
Classifier: Operating System :: Microsoft :: Windows :: Windows 10
Classifier: Operating System :: Microsoft :: Windows :: Windows 11
Classifier: Programming Language :: Python
Classifier: Programming Language :: Python :: Implementation :: CPython
Classifier: Programming Language :: Python :: Implementation :: PyPy
Classifier: Programming Language :: Python :: 3.10
Classifier: Programming Language :: Python :: 3.11
Classifier: Programming Language :: Python :: 3.12
Requires-Python: >=3.10
License-File: LICENSE
Requires-Dist: pyserial
